{"metadata": {"dbt_schema_version": "https://schemas.getdbt.com/dbt/run-results/v4.json", "dbt_version": "1.5.0", "generated_at": "2023-06-25T08:10:17.917953Z", "invocation_id": "767dc537-ff88-44eb-991f-1451768ae2d8", "env": {}}, "results": [{"status": "success", "timing": [{"name": "compile", "started_at": "2023-06-25T08:10:15.392871Z", "completed_at": "2023-06-25T08:10:15.397701Z"}, {"name": "execute", "started_at": "2023-06-25T08:10:15.398958Z", "completed_at": "2023-06-25T08:10:15.726892Z"}], "thread_id": "Thread-1", "execution_time": 0.33740997314453125, "adapter_response": {"_message": "CREATE VIEW", "code": "CREATE VIEW", "rows_affected": -1}, "message": "CREATE VIEW", "failures": null, "unique_id": "model.levergreen_dbt.stg_greenhouse__job_departments"}, {"status": "success", "timing": [{"name": "compile", "started_at": "2023-06-25T08:10:15.734704Z", "completed_at": "2023-06-25T08:10:15.739351Z"}, {"name": "execute", "started_at": "2023-06-25T08:10:15.740582Z", "completed_at": "2023-06-25T08:10:15.990306Z"}], "thread_id": "Thread-1", "execution_time": 0.25914740562438965, "adapter_response": {"_message": "CREATE VIEW", "code": "CREATE VIEW", "rows_affected": -1}, "message": "CREATE VIEW", "failures": null, "unique_id": "model.levergreen_dbt.stg_greenhouse__jobs_outline"}, {"status": "success", "timing": [{"name": "compile", "started_at": "2023-06-25T08:10:15.998976Z", "completed_at": "2023-06-25T08:10:16.003876Z"}, {"name": "execute", "started_at": "2023-06-25T08:10:16.005099Z", "completed_at": "2023-06-25T08:10:16.248179Z"}], "thread_id": "Thread-1", "execution_time": 0.25252795219421387, "adapter_response": {"_message": "CREATE VIEW", "code": "CREATE VIEW", "rows_affected": -1}, "message": "CREATE VIEW", "failures": null, "unique_id": "model.levergreen_dbt.stg_lever__jobs_outline"}, {"status": "success", "timing": [{"name": "compile", "started_at": "2023-06-25T08:10:16.274662Z", "completed_at": "2023-06-25T08:10:16.311553Z"}, {"name": "execute", "started_at": "2023-06-25T08:10:16.312915Z", "completed_at": "2023-06-25T08:10:17.485842Z"}], "thread_id": "Thread-1", "execution_time": 1.2148151397705078, "adapter_response": {"_message": "SELECT 26167", "code": "SELECT", "rows_affected": 26167}, "message": "SELECT 26167", "failures": null, "unique_id": "model.levergreen_dbt.all_job_postings"}, {"status": "success", "timing": [{"name": "compile", "started_at": "2023-06-25T08:10:17.494412Z", "completed_at": "2023-06-25T08:10:17.498755Z"}, {"name": "execute", "started_at": "2023-06-25T08:10:17.499986Z", "completed_at": "2023-06-25T08:10:17.760465Z"}], "thread_id": "Thread-1", "execution_time": 0.2694976329803467, "adapter_response": {"_message": "SELECT 652", "code": "SELECT", "rows_affected": 652}, "message": "SELECT 652", "failures": null, "unique_id": "model.levergreen_dbt.active_job_postings"}], "elapsed_time": 3.5363495349884033, "args": {"log_path": "/home/runner/work/job-board-scraper/job-board-scraper/levergreen_dbt/logs", "write_json": true, "version_check": true, "static_parser": true, "profiles_dir": "/home/runner/work/job-board-scraper/job-board-scraper/levergreen_dbt", "send_anonymous_usage_stats": true, "enable_legacy_logger": false, "favor_state": false, "warn_error_options": {"include": [], "exclude": []}, "exclude": [], "macro_debugging": false, "log_format": "default", "quiet": false, "select": [], "indirect_selection": "eager", "use_colors": true, "strict_mode": false, "project_dir": "/home/runner/work/job-board-scraper/job-board-scraper/levergreen_dbt", "printer_width": 80, "partial_parse": true, "print": true, "use_colors_file": true, "log_level_file": "debug", "cache_selected_only": false, "vars": {}, "populate_cache": true, "which": "run", "log_level": "info", "defer": false, "introspect": true, "log_format_file": "debug"}}