{"metadata": {"dbt_schema_version": "https://schemas.getdbt.com/dbt/run-results/v4.json", "dbt_version": "1.5.0", "generated_at": "2023-06-21T07:30:05.698888Z", "invocation_id": "eefbf5cf-2ca8-4988-a549-bf81c9b0fd3d", "env": {}}, "results": [{"status": "success", "timing": [{"name": "compile", "started_at": "2023-06-21T07:30:02.696467Z", "completed_at": "2023-06-21T07:30:02.701704Z"}, {"name": "execute", "started_at": "2023-06-21T07:30:02.702956Z", "completed_at": "2023-06-21T07:30:03.089574Z"}], "thread_id": "Thread-1", "execution_time": 0.3965494632720947, "adapter_response": {"_message": "CREATE VIEW", "code": "CREATE VIEW", "rows_affected": -1}, "message": "CREATE VIEW", "failures": null, "unique_id": "model.levergreen_dbt.stg_greenhouse__job_departments"}, {"status": "success", "timing": [{"name": "compile", "started_at": "2023-06-21T07:30:03.097235Z", "completed_at": "2023-06-21T07:30:03.102248Z"}, {"name": "execute", "started_at": "2023-06-21T07:30:03.103456Z", "completed_at": "2023-06-21T07:30:03.415882Z"}], "thread_id": "Thread-1", "execution_time": 0.3221886157989502, "adapter_response": {"_message": "CREATE VIEW", "code": "CREATE VIEW", "rows_affected": -1}, "message": "CREATE VIEW", "failures": null, "unique_id": "model.levergreen_dbt.stg_greenhouse__jobs_outline"}, {"status": "success", "timing": [{"name": "compile", "started_at": "2023-06-21T07:30:03.423764Z", "completed_at": "2023-06-21T07:30:03.428945Z"}, {"name": "execute", "started_at": "2023-06-21T07:30:03.430150Z", "completed_at": "2023-06-21T07:30:03.727316Z"}], "thread_id": "Thread-1", "execution_time": 0.3070530891418457, "adapter_response": {"_message": "CREATE VIEW", "code": "CREATE VIEW", "rows_affected": -1}, "message": "CREATE VIEW", "failures": null, "unique_id": "model.levergreen_dbt.stg_lever__jobs_outline"}, {"status": "success", "timing": [{"name": "compile", "started_at": "2023-06-21T07:30:03.754425Z", "completed_at": "2023-06-21T07:30:03.790813Z"}, {"name": "execute", "started_at": "2023-06-21T07:30:03.792128Z", "completed_at": "2023-06-21T07:30:05.145617Z"}], "thread_id": "Thread-1", "execution_time": 1.39467453956604, "adapter_response": {"_message": "SELECT 23571", "code": "SELECT", "rows_affected": 23571}, "message": "SELECT 23571", "failures": null, "unique_id": "model.levergreen_dbt.all_job_postings"}, {"status": "success", "timing": [{"name": "compile", "started_at": "2023-06-21T07:30:05.154115Z", "completed_at": "2023-06-21T07:30:05.158693Z"}, {"name": "execute", "started_at": "2023-06-21T07:30:05.159884Z", "completed_at": "2023-06-21T07:30:05.499404Z"}], "thread_id": "Thread-1", "execution_time": 0.3489203453063965, "adapter_response": {"_message": "SELECT 636", "code": "SELECT", "rows_affected": 636}, "message": "SELECT 636", "failures": null, "unique_id": "model.levergreen_dbt.active_job_postings"}], "elapsed_time": 4.85666036605835, "args": {"select": [], "exclude": [], "profiles_dir": "/home/runner/work/job-board-scraper/job-board-scraper/levergreen_dbt", "strict_mode": false, "send_anonymous_usage_stats": true, "cache_selected_only": false, "which": "run", "use_colors": true, "enable_legacy_logger": false, "use_colors_file": true, "log_path": "/home/runner/work/job-board-scraper/job-board-scraper/levergreen_dbt/logs", "log_format": "default", "partial_parse": true, "printer_width": 80, "project_dir": "/home/runner/work/job-board-scraper/job-board-scraper/levergreen_dbt", "print": true, "warn_error_options": {"include": [], "exclude": []}, "defer": false, "log_level": "info", "favor_state": false, "static_parser": true, "macro_debugging": false, "version_check": true, "populate_cache": true, "vars": {}, "introspect": true, "log_level_file": "debug", "indirect_selection": "eager", "write_json": true, "quiet": false, "log_format_file": "debug"}}